backtrader_bybit/__init__.py
backtrader_bybit/bybit_broker.py
backtrader_bybit/bybit_feed.py
backtrader_bybit/bybit_store.py
backtrader_bybit/enums.py
backtrader_bybit-2.0.9.dist-info/LICENSE
backtrader_bybit-2.0.9.dist-info/METADATA
backtrader_bybit-2.0.9.dist-info/WHEEL
backtrader_bybit-2.0.9.dist-info/top_level.txt
backtrader_bybit-2.0.9.dist-info/RECORD
