Metadata-Version: 2.1
Name: backtrader-bybit
Version: 2.0.9
Summary: Bybit API integration with Backtrader
Home-page: https://github.com/WISEPLAT/backtrader_bybit
Author: wiseplat
Author-email: oshpagin@gmail.com
License: MIT License
Project-URL: Documentation, https://github.com/WISEPLAT/backtrader_bybit/blob/master/README.md
Keywords: trading,development
Classifier: Development Status :: 5 - Production/Stable
Classifier: Intended Audience :: Developers
Classifier: Intended Audience :: Financial and Insurance Industry
Classifier: Topic :: Software Development
Classifier: Topic :: Office/Business :: Financial
Classifier: Programming Language :: Python :: 3.9
Classifier: Programming Language :: Python :: 3.10
Classifier: Programming Language :: Python :: 3.11
Classifier: License :: OSI Approved :: MIT License
Classifier: Operating System :: OS Independent
Requires-Python: >=3.7
License-File: LICENSE
Requires-Dist: pybit
Requires-Dist: pycryptodome
Requires-Dist: backtrader
Requires-Dist: pandas
Requires-Dist: matplotlib
